[
  {
    "ItemCode":"ITM0001",
    "ItemName":"Special Nasi Goreng with Fried Chicken",
    "Description":"Fried rice with pappadum, fried chicken, sambal and fried egg.",
    "NutritionInfo":"",
    "Price":1200,
    "MainCategoryId":"MCAT004",
    "SubcategoryId":"SCAT003",
    "Rating":5,
    "ThumbImgUrlOne":"img_itm_001",
    "ThumbImgUrlTwo":"img_cart_itm_001",
    "ImageUrl":"img_itm_full_001"
  },
  {
    "ItemCode":"ITM0002",
    "ItemName":"Hainan Curry Chicken Chop",
    "Description":"Deep-fried chicken coated with curry sauce, served with chicken rice, fried egg and sliced cucumbers.",
    "NutritionInfo":"",
    "Price":1450,
    "MainCategoryId":"MCAT004",
    "SubcategoryId":"SCAT003",
    "Rating":3,
    "ThumbImgUrlOne":"img_itm_002",
    "ThumbImgUrlTwo":"img_cart_itm_002",
    "ImageUrl":"img_itm_full_002"
  },
  {
    "ItemCode":"ITM0003",
    "ItemName":"Oriental Beef Chop",
    "Description":"Deep-fried beef coated with black pepper sauce, served with beef rice, fried egg and sliced cucumber.",
    "NutritionInfo":"",
    "Price":1350,
    "MainCategoryId":"MCAT004",
    "SubcategoryId":"SCAT004",
    "Rating":5,
    "ThumbImgUrlOne":"img_itm_003",
    "ThumbImgUrlTwo":"img_cart_itm_003",
    "ImageUrl":"img_itm_full_003"
  },
  {
    "ItemCode":"ITM0004",
    "ItemName":"Biryani Rice with Prawns",
    "Description":"Deep-fried prawns coated with black pepper sauce, served with rice, fried egg and sliced cucumber.",
    "NutritionInfo":"",
    "Price":1500,
    "MainCategoryId":"MCAT004",
    "SubcategoryId":"SCAT007",
    "Rating":4,
    "ThumbImgUrlOne":"img_itm_004",
    "ThumbImgUrlTwo":"img_cart_itm_004",
    "ImageUrl":"img_itm_full_004"
  },
  {
    "ItemCode":"ITM0005",
    "ItemName":"Nasi Lemak with Veg Curry",
    "Description":"Nasi Lemak comes with aromatic coconut milk infused in steamed rice served with curry chicken, fried anchovies, fried peanuts, hard boiled egg, our delicious daily made spicy sambal and cucumber slices.*Gluten free",
    "NutritionInfo":"",
    "Price":900,
    "MainCategoryId":"MCAT004",
    "SubcategoryId":"SCAT001",
    "Rating":5,
    "ThumbImgUrlOne":"img_itm_005",
    "ThumbImgUrlTwo":"img_cart_itm_005",
    "ImageUrl":"img_itm_full_005"
  },
  {
    "ItemCode":"ITM0006",
    "ItemName":"Special Biryani Rice with Sambal Eggplant, Fried pork",
    "Description":"Pappa special Nasi Biryani comes with aromatic Indian spiced rice, a medley of sambal eggplant, fried pork and sambal prawns.",
    "NutritionInfo":"",
    "Price":1100,
    "MainCategoryId":"MCAT004",
    "SubcategoryId":"SCAT005",
    "Rating":4,
    "ThumbImgUrlOne":"img_itm_006",
    "ThumbImgUrlTwo":"img_cart_itm_006",
    "ImageUrl":"img_itm_full_006"
  },
  {
    "ItemCode":"ITM0007",
    "ItemName":"Pan Mee Noodle Soup",
    "Description":"Flour noodles in freshly boiled  anchovy based soup. Served with minced seafood, fried anchovies, mushrooms, spinach and topped with half boiled egg (pan mee soup chilli on the side).",
    "NutritionInfo":"",
    "Price":600,
    "MainCategoryId":"MCAT005",
    "SubcategoryId":"SCAT006",
    "Rating":3,
    "ThumbImgUrlOne":"img_itm_007",
    "ThumbImgUrlTwo":"img_cart_itm_007",
    "ImageUrl":"img_itm_full_007"
  },
  {
    "ItemCode":"ITM0008",
    "ItemName":"Fried Rice Noodles",
    "Description":"Wok-fried rice starch noodles with chicken slices, prawns, egg, bean sprouts, chives and red chilli. This dish is spicy.",
    "NutritionInfo":"",
    "Price":900,
    "MainCategoryId":"MCAT005",
    "SubcategoryId":"SCAT003",
    "Rating":5,
    "ThumbImgUrlOne":"img_itm_008",
    "ThumbImgUrlTwo":"img_cart_itm_008",
    "ImageUrl":"img_itm_full_008"
  },
  {
    "ItemCode":"ITM0009",
    "ItemName":"Chilli Pan Mee",
    "Description":"Dry flour noodles served with minced crab, fried anchovies, chilli pan mee chilli, mushrooms, fried shallots, spinach and topped with half boiled egg. Stir well before consuming.",
    "NutritionInfo":"",
    "Price":1200,
    "MainCategoryId":"MCAT005",
    "SubcategoryId":"SCAT008",
    "Rating":4,
    "ThumbImgUrlOne":"img_itm_009",
    "ThumbImgUrlTwo":"img_cart_itm_009",
    "ImageUrl":"img_itm_full_009"
  },
  {
    "ItemCode":"ITM0010",
    "ItemName":"Dry Curry Egg Noodles with Curry",
    "Description":"Egg noodles doused in rich curry gravy and served with curry, chop sum and red chilli.",
    "NutritionInfo":"",
    "Price":600,
    "MainCategoryId":"MCAT005",
    "SubcategoryId":"SCAT001",
    "Rating":4,
    "ThumbImgUrlOne":"img_itm_010",
    "ThumbImgUrlTwo":"img_cart_itm_010",
    "ImageUrl":"img_itm_full_010"
  },
  {
    "ItemCode":"ITM0011",
    "ItemName":"Ipoh Koay Teow Soup with Prawns",
    "Description":"Thin flat rice noodles in our freshly boiled daily chicken soup and prawn head broth. Topped with prawns, chicken slices, bean sprouts, chives and red chilli.",
    "NutritionInfo":"",
    "Price":1400,
    "MainCategoryId":"MCAT005",
    "SubcategoryId":"SCAT006",
    "Rating":5,
    "ThumbImgUrlOne":"img_itm_011",
    "ThumbImgUrlTwo":"img_cart_itm_011",
    "ImageUrl":"img_itm_full_011"
  },
  {
    "ItemCode":"ITM0012",
    "ItemName":"Crispy Egg Noodles",
    "Description":"Wok-fried egg noodles with egg gravy, prawns, fish cakes and chicken slices.",
    "NutritionInfo":"",
    "Price":950,
    "MainCategoryId":"MCAT005",
    "SubcategoryId":"SCAT003",
    "Rating":5,
    "ThumbImgUrlOne":"img_itm_012",
    "ThumbImgUrlTwo":"img_cart_itm_012",
    "ImageUrl":"img_itm_full_012"
  },
  {
    "ItemCode":"ITM0013",
    "ItemName":"Vegetable Spring Roll With Plum Sauce",
    "Description":"4 Pieces - Serves 2.",
    "NutritionInfo":"",
    "Price":300,
    "MainCategoryId":"MCAT001",
    "SubcategoryId":"SCAT001",
    "Rating":3,
    "ThumbImgUrlOne":"img_itm_013",
    "ThumbImgUrlTwo":"img_cart_itm_013",
    "ImageUrl":"img_itm_full_013"
  },
  {
    "ItemCode":"ITM0014",
    "ItemName":"Chicken Won Ton With Plum Sauce",
    "Description":"4 Pieces - Serves 2.",
    "NutritionInfo":"",
    "Price":450,
    "MainCategoryId":"MCAT001",
    "SubcategoryId":"SCAT003",
    "Rating":4,
    "ThumbImgUrlOne":"img_itm_014",
    "ThumbImgUrlTwo":"img_cart_itm_014",
    "ImageUrl":"img_itm_full_014"
  },
  {
    "ItemCode":"ITM0015",
    "ItemName":"French Fries",
    "Description":"Serves 2.",
    "NutritionInfo":"",
    "Price":350,
    "MainCategoryId":"MCAT001",
    "SubcategoryId":"SCAT001",
    "Rating":3,
    "ThumbImgUrlOne":"img_itm_015",
    "ThumbImgUrlTwo":"img_cart_itm_015",
    "ImageUrl":"img_itm_full_015"
  }
]
